{
  "feature": "wythers:vegetation/tree/mediterranean_cypress",
  "placement": [
    {
      "type": "minecraft:count",
      "count": 30
    },
    {
      "type": "minecraft:in_square"
    },
    {
      "type": "minecraft:noise_based_count",
      "noise_to_count_ratio": 1,
      "noise_factor": 150,
      "noise_offset": 0
    },
    {
      "type": "minecraft:noise_based_count",
      "noise_to_count_ratio": -1,
      "noise_factor": 250,
      "noise_offset": -0.09
    },
    {
      "type": "minecraft:noise_based_count",
      "noise_to_count_ratio": 1,
      "noise_factor": 250,
      "noise_offset": -0.07
    },
    {
      "type": "minecraft:heightmap",
      "heightmap": "MOTION_BLOCKING"
    },
    {
      "type": "minecraft:block_predicate_filter",
      "predicate": {
        "type": "minecraft:would_survive",
        "state": {
          "Name": "minecraft:oak_sapling",
          "Properties": {
            "stage": "0"
          }
        }
      }
    },
    {
      "type": "minecraft:block_predicate_filter",
      "predicate": {
        "type": "minecraft:not",
        "predicate": {
          "type": "minecraft:matching_blocks",
          "offset": [
            0,
            -2,
            0
          ],
          "blocks": "minecraft:rooted_dirt"
        }
      }
    },
    {
      "type": "minecraft:block_predicate_filter",
      "predicate": {
        "type": "minecraft:not",
        "predicate": {
          "type": "minecraft:matching_blocks",
          "offset": [
            0,
            -3,
            0
          ],
          "blocks": "minecraft:packed_mud"
        }
      }
    }
  ]
}
